{"version":2,"baseVals":{"rating":3,"decay":0.9,"echo_zoom":1,"wave_mode":6,"wave_dots":1,"modwavealphabyvolume":1,"wave_brighten":0,"wrap":0,"wave_a":0,"wave_smoothing":0,"zoomexp":1.00016,"zoom":0.98686,"warp":0.01,"sx":0.9998,"wave_r":0,"wave_g":0,"wave_b":0,"ob_size":0,"ib_size":0,"ib_r":0,"ib_g":0,"ib_b":0,"mv_a":0},"shapes":[{"baseVals":{"textured":1,"rad":2.4266,"tex_zoom":0.41583,"g":1,"b":1,"a":0,"r2":1,"b2":1,"a2":1,"enabled":0},"init_eqs_str":"","frame_eqs_str":""},{"baseVals":{"x":0.9,"y":0.8,"rad":0.49138,"tex_zoom":4.66674,"g":1,"b":1,"r2":1,"b2":1,"border_a":0,"enabled":0},"init_eqs_str":"","frame_eqs_str":""},{"baseVals":{"enabled":0},"init_eqs_str":"","frame_eqs_str":""},{"baseVals":{"enabled":0},"init_eqs_str":"","frame_eqs_str":""}],"waves":[{"baseVals":{"enabled":1,"samples":201,"sep":135,"spectrum":1,"thick":1,"scaling":2.92905,"a":0},"init_eqs_str":"a['q21'] = 0; a['q22'] = 0; a['t1'] = 0; a['q23'] = 0; a['k'] = 0; a['t2'] = 0; a['q31'] = 0; a['yscl'] = 0; ","frame_eqs_str":"a['t1']=0; a['k']=0; a['r']=0; a['g']=0; a['b']=0; a['t2']=0; a['q31']=1; a['yscl']=div(1,(a['q22']-a['q21']));","point_eqs_str":"a['x']=a['value1']; a['y']=(a['q21']+((a['q22']*a['t1'])*0.005)); a['r']=a['x']; a['g']=a['x']; a['b']=a['x']; a['x']=a['q23']; a['t1']=(a['t1']+1); a['a']=1;"},{"baseVals":{"samples":201,"sep":140,"spectrum":1,"additive":1,"scaling":1.0001,"smoothing":0.4999,"enabled":0},"init_eqs_str":"","frame_eqs_str":"t2=0;","point_eqs_str":"x=0.2+value1;\ny=q21+q22*t2*0.005;\n\nt2=t2+1;\nr=1;\ng=1;\nb=1;\n\na=1;\n\n"},{"baseVals":{"samples":201,"thick":1,"additive":1,"scaling":0.06811,"smoothing":0,"enabled":0},"init_eqs_str":"","frame_eqs_str":"t3=0;","point_eqs_str":"x=0.0003+q23;\ny=q21+q22*t3*0.005;\nt3=t3+1;\nr=1;\ng=1;\nb=1;\na=1;"},{"baseVals":{"enabled":0},"init_eqs_str":"","frame_eqs_str":"","point_eqs_str":""}],"init_eqs_str":"a['v5'] = 0; a['q12'] = 0; a['v3'] = 0; a['q18'] = 0; a['q22'] = 0; a['q21'] = 0; a['q13'] = 0; a['meanbass_att'] = 0; a['v4'] = 0; a['q15'] = 0; a['q6'] = 0; a['q1'] = 0; a['q5'] = 0; a['q9'] = 0; a['v6'] = 0; a['lastbeat'] = 0; a['beatrate'] = 0; a['q23'] = 0; a['q24'] = 0; a['q11'] = 0; a['peakbass_att'] = 0; a['q10'] = 0; a['v7'] = 0; a['v8'] = 0; a['q4'] = 0; a['q16'] = 0; a['att'] = 0; a['volume'] = 0; a['beat'] = 0; a['q17'] = 0; a['q2'] = 0; a['q14'] = 0; a['v1'] = 0; a['q3'] = 0; a['q7'] = 0; a['v2'] = 0; a['q20'] = 0; a['q8'] = 0; a['q3']=0; a['v1']=0.2; a['v2']=0.63; a['v3']=0.34; a['v4']=0.5; a['v5']=0.6; a['v6']=0.7; a['v7']=0.8; a['v8']=0.9;","frame_eqs_str":"a['volume']=(0.3*((a['bass']+a['mid'])+a['att'])); a['beatrate']=((Math.abs(equal(a['beatrate'], 0))>0.00001)?(1):(((Math.abs(below(a['volume'], 0.01))>0.00001)?(1):(a['beatrate'])))); a['lastbeat']=((Math.abs(equal(a['lastbeat'], 0))>0.00001)?(a['time']):(a['lastbeat'])); a['meanbass_att']=(0.1*((a['meanbass_att']*9)+a['bass_att'])); a['beat']=((Math.abs(above(a['volume'], 0.8))>0.00001)?(((Math.abs(below((a['peakbass_att']-a['bass_att']), (0.05*a['peakbass_att'])))>0.00001)?(((Math.abs(above((a['time']-a['lastbeat']), (0.1+(0.5*(a['beatrate']-0.1)))))>0.00001)?(1):(0))):(0))):(0)); a['beatrate']=Math.max(((Math.abs(a['beat'])>0.00001)?(((Math.abs(below((a['time']-a['lastbeat']), (2*a['beatrate'])))>0.00001)?((0.5*((a['beatrate']+a['time'])-a['lastbeat']))):(a['beatrate']))):(a['beatrate'])), 0.1); a['peakbass_att']=((Math.abs(equal(a['beat'], 0))>0.00001)?(((Math.abs(above((a['time']-a['lastbeat']), (2*a['beatrate'])))>0.00001)?((a['peakbass_att']*0.95)):((a['peakbass_att']*0.995)))):(a['bass_att'])); a['lastbeat']=((Math.abs(a['beat'])>0.00001)?(a['time']):(a['lastbeat'])); a['peakbass_att']=Math.max(((Math.abs(a['beat'])>0.00001)?(a['bass_att']):(a['peakbass_att'])), (1.1*a['meanbass_att'])); a['q1']=a['aspectx']; a['q2']=a['aspecty']; a['q21']=(0.5-div(0.5,a['q2'])); a['q22']=div(1,a['q2']); a['q23']=(0.5-div(0.5,a['q1'])); a['q20']=0; a['q24']=(1-a['q21']); a['v1']=(a['v1']+0.003); a['v2']=(a['v2']-0.004); a['v3']=(a['v3']+0.005); a['v4']=(a['v4']-0.006); a['v5']=(a['v5']+0.007); a['v6']=(a['v6']-0.008); a['v7']=(a['v7']+0.009); a['v8']=(a['v8']-0.01); a['q3']=(0.5+(0.45*Math.sin((a['v1']+(1*0.3))))); a['q4']=(0.5+(0.45*Math.cos(((a['v1']*0.3783)+(1*0.336))))); a['q5']=(0.5+(0.45*Math.sin((a['v2']+(2*0.3))))); a['q6']=(0.5+(0.45*Math.cos(((a['v2']*0.4783)+(2*0.336))))); a['q7']=(0.5+(0.45*Math.sin((a['v3']+(3*0.3))))); a['q8']=(0.5+(0.45*Math.cos(((a['v3']*0.5783)+(3*0.336))))); a['q9']=(0.5+(0.45*Math.sin((a['v4']+(4*0.3))))); a['q10']=(0.5+(0.45*Math.cos(((a['v4']*0.6783)+(4*0.336))))); a['q11']=(0.5+(0.45*Math.sin((a['v5']+(5*0.3))))); a['q12']=(0.5+(0.45*Math.cos(((a['v5']*0.7783)+(5*0.336))))); a['q13']=(0.5+(0.45*Math.sin((a['v6']+(6*0.3))))); a['q14']=(0.5+(0.45*Math.cos(((a['v6']*0.8783)+(6*0.336))))); a['q15']=(0.5+(0.45*Math.sin((a['v7']+(7*0.3))))); a['q16']=(0.5+(0.45*Math.cos(((a['v7']*0.9783)+(7*0.336))))); a['q17']=(0.5+(0.45*Math.sin((a['v8']+(8*0.3))))); a['q18']=(0.5+(0.45*Math.cos(((a['v8']*0.2783)+(8*0.336)))));","pixel_eqs_str":"","warp":"uniform sampler2D sampler_rand00;\n shader_body { \n  vec3 v_1;\n  vec2 pq_2;\n  vec3 vs_3;\n  vec3 ret_4;\n  vec2 tmpvar_5;\n  tmpvar_5.x = q20;\n  tmpvar_5.y = 0.94;\n  vec2 tmpvar_6;\n  tmpvar_6.x = q2;\n  tmpvar_6.y = q1;\n  vec2 tmpvar_7;\n  tmpvar_7 = (uv - 0.5);\n  pq_2 = ((tmpvar_7 * tmpvar_6) + 0.5);\n  vec2 tmpvar_8;\n  tmpvar_8.x = q3;\n  tmpvar_8.y = q4;\n  v_1.xy = (pq_2 - tmpvar_8);\n  v_1.z = 0.1;\n  float tmpvar_9;\n  tmpvar_9 = sqrt(dot (v_1, v_1));\n  vec3 tmpvar_10;\n  tmpvar_10 = normalize(v_1);\n  vs_3.xy = ((tmpvar_10.xy * (texture (sampler_pc_main, tmpvar_5).x * 2.0)) * tmpvar_10.zz);\n  vec2 tmpvar_11;\n  tmpvar_11.x = q20;\n  tmpvar_11.y = 0.9;\n  vec2 tmpvar_12;\n  tmpvar_12.x = q5;\n  tmpvar_12.y = q6;\n  v_1.xy = (pq_2 - tmpvar_12);\n  v_1.z = 0.2;\n  vec3 tmpvar_13;\n  tmpvar_13 = normalize(v_1);\n  vs_3.z = (tmpvar_9 + sqrt(dot (v_1, v_1)));\n  vs_3.xy = (vs_3.xy + ((tmpvar_13.xy * texture (sampler_pc_main, tmpvar_11).x) * tmpvar_13.zz));\n  vec2 tmpvar_14;\n  tmpvar_14.x = q20;\n  tmpvar_14.y = 0.85;\n  vec2 tmpvar_15;\n  tmpvar_15.x = q7;\n  tmpvar_15.y = q8;\n  v_1.xy = (pq_2 - tmpvar_15);\n  v_1.z = 0.3;\n  vec3 tmpvar_16;\n  tmpvar_16 = normalize(v_1);\n  vs_3.z = (vs_3.z + sqrt(dot (v_1, v_1)));\n  vs_3.xy = (vs_3.xy + ((tmpvar_16.xy * texture (sampler_pc_main, tmpvar_14).x) * tmpvar_16.zz));\n  vec2 tmpvar_17;\n  tmpvar_17.x = q20;\n  tmpvar_17.y = 0.8;\n  vec2 tmpvar_18;\n  tmpvar_18.x = q9;\n  tmpvar_18.y = q10;\n  v_1.xy = (pq_2 - tmpvar_18);\n  v_1.z = 0.4;\n  vec3 tmpvar_19;\n  tmpvar_19 = normalize(v_1);\n  vs_3.z = (vs_3.z + sqrt(dot (v_1, v_1)));\n  vs_3.xy = (vs_3.xy + ((tmpvar_19.xy * texture (sampler_pc_main, tmpvar_17).x) * tmpvar_19.zz));\n  vec2 tmpvar_20;\n  tmpvar_20.x = q20;\n  tmpvar_20.y = 0.75;\n  vec2 tmpvar_21;\n  tmpvar_21.x = q11;\n  tmpvar_21.y = q12;\n  v_1.xy = (pq_2 - tmpvar_21);\n  v_1.z = 0.5;\n  vec3 tmpvar_22;\n  tmpvar_22 = normalize(v_1);\n  vs_3.z = (vs_3.z + sqrt(dot (v_1, v_1)));\n  vs_3.xy = (vs_3.xy + ((tmpvar_22.xy * texture (sampler_pc_main, tmpvar_20).x) * tmpvar_22.zz));\n  vec2 tmpvar_23;\n  tmpvar_23.x = q20;\n  tmpvar_23.y = 0.6;\n  vec2 tmpvar_24;\n  tmpvar_24.x = q13;\n  tmpvar_24.y = q14;\n  v_1.xy = (pq_2 - tmpvar_24);\n  v_1.z = 0.6;\n  vec3 tmpvar_25;\n  tmpvar_25 = normalize(v_1);\n  vs_3.z = (vs_3.z + sqrt(dot (v_1, v_1)));\n  vs_3.xy = (vs_3.xy + ((tmpvar_25.xy * texture (sampler_pc_main, tmpvar_23).x) * tmpvar_25.zz));\n  vec2 tmpvar_26;\n  tmpvar_26.x = q20;\n  tmpvar_26.y = 0.35;\n  vec2 tmpvar_27;\n  tmpvar_27.x = q15;\n  tmpvar_27.y = q16;\n  v_1.xy = (pq_2 - tmpvar_27);\n  v_1.z = 0.7;\n  vec3 tmpvar_28;\n  tmpvar_28 = normalize(v_1);\n  vs_3.z = (vs_3.z + sqrt(dot (v_1, v_1)));\n  vs_3.xy = (vs_3.xy + ((tmpvar_28.xy * texture (sampler_pc_main, tmpvar_26).x) * tmpvar_28.zz));\n  vec2 tmpvar_29;\n  tmpvar_29.x = q20;\n  tmpvar_29.y = 0.2;\n  vec2 tmpvar_30;\n  tmpvar_30.x = q17;\n  tmpvar_30.y = q18;\n  v_1.xy = (pq_2 - tmpvar_30);\n  v_1.z = 0.8;\n  float tmpvar_31;\n  tmpvar_31 = sqrt(dot (v_1, v_1));\n  vec3 tmpvar_32;\n  tmpvar_32 = normalize(v_1);\n  v_1 = tmpvar_32;\n  vs_3.z = (vs_3.z + tmpvar_31);\n  vs_3.xy = (vs_3.xy + ((tmpvar_32.xy * texture (sampler_pc_main, tmpvar_29).x) * tmpvar_32.zz));\n  ret_4 = texture (sampler_rand00, (((\n    (tmpvar_7 * vs_3.zz)\n   * tmpvar_6) + 0.5) + ((\n    ((8.0 - vs_3.zz) * vs_3.xy)\n   * 0.02) * tmpvar_6))).xyz;\n  ret_4 = ((texture (sampler_main, (uv - \n    (((vs_3.xy * 0.02) * vs_3.zz) / tmpvar_6)\n  )).xyz * 0.98) + (ret_4 * 0.02));\n  vec4 tmpvar_33;\n  tmpvar_33.w = 1.0;\n  tmpvar_33.xyz = ret_4;\n  ret = tmpvar_33.xyz;\n }","comp":" shader_body { \n  vec3 ret_1;\n  vec4 tmpvar_2;\n  tmpvar_2 = texture (sampler_fw_main, uv);\n  ret_1.x = ((sin(\n    ((25.13274 * tmpvar_2.x) + (12.56637 * q3))\n  ) * 0.5) + 0.5);\n  float tmpvar_3;\n  tmpvar_3 = (q6 * 6.283185);\n  ret_1.y = ((sin(\n    ((25.13274 * tmpvar_2.y) + tmpvar_3)\n  ) * 0.5) + 0.5);\n  ret_1.z = ((sin(\n    ((25.13274 * tmpvar_2.z) + (18.84956 * q7))\n  ) * 0.5) + 0.5);\n  ret_1 = (ret_1 - (ret_1 * (1.0 - \n    sin((1.570796 * ret_1))\n  )));\n  ret_1.x = sin(((3.141593 * ret_1.x) + (0.6283185 * q4)));\n  ret_1.y = sin(((3.141593 * ret_1.y) + (0.6283185 * q5)));\n  ret_1.z = sin(((3.141593 * ret_1.z) + (tmpvar_3 * 0.1)));\n  ret_1 = (ret_1 - (ret_1 * (1.0 - \n    sin((1.570796 * ret_1))\n  )));\n  ret_1 = (ret_1 * ret_1);\n  vec4 tmpvar_4;\n  tmpvar_4.w = 1.0;\n  tmpvar_4.xyz = ret_1;\n  ret = tmpvar_4.xyz;\n }"}