{"version":2,"baseVals":{"rating":0,"gammaadj":1.9,"echo_zoom":1.169,"wave_mode":4,"additivewave":1,"wave_thick":1,"wave_a":0,"wave_scale":0.26,"wave_smoothing":0.9,"modwavealphastart":0.63,"modwavealphaend":0.87,"warpscale":3.138,"zoom":0.99703,"warp":0.01,"wave_r":0.5,"wave_g":0.5,"wave_b":0.5,"wave_y":0.72,"ob_size":0,"ob_r":0.1,"ob_g":0.08,"ob_a":0.6,"ib_size":0,"ib_r":1,"ib_g":1,"ib_b":1,"ib_a":0.1,"mv_a":0},"shapes":[{"baseVals":{"enabled":0},"init_eqs_str":"","frame_eqs_str":""},{"baseVals":{"enabled":0},"init_eqs_str":"","frame_eqs_str":""},{"baseVals":{"enabled":0},"init_eqs_str":"","frame_eqs_str":""},{"baseVals":{"enabled":0},"init_eqs_str":"","frame_eqs_str":""}],"waves":[{"baseVals":{"enabled":0},"init_eqs_str":"","frame_eqs_str":"","point_eqs_str":""},{"baseVals":{"enabled":0},"init_eqs_str":"","frame_eqs_str":"","point_eqs_str":""},{"baseVals":{"enabled":0},"init_eqs_str":"","frame_eqs_str":"","point_eqs_str":""},{"baseVals":{"enabled":0},"init_eqs_str":"","frame_eqs_str":"","point_eqs_str":""}],"init_eqs_str":"a['thresh'] = 0; a['dx_r'] = 0; a['dy_r'] = 0; a['q1'] = 0; a['q2'] = 0; a['q3'] = 0;","frame_eqs_str":"a['cx']=(a['cx']+(0.210*((0.60*Math.sin((0.374*a['time'])))+(0.40*Math.sin((0.294*a['time'])))))); a['cy']=(a['cy']+(0.210*((0.60*Math.sin((0.393*a['time'])))+(0.40*Math.sin((0.223*a['time'])))))); a['q1']=((0.11*Math.sin((a['time']*1.1)))+(0.1*Math.cos((a['time']*0.43)))); a['q2']=((0.11*Math.sin((a['time']*0.92)))+(0.1*Math.cos((a['time']*1.1)))); a['q3']=((0.11*Math.sin((a['time']*0.22)))+(0.1*Math.cos((a['time']*0.33))));","pixel_eqs_str":"a['zoom']=(1.0+(0.05*Math.sin(((((a['ang']*9)-(10*Math.sin(a['time'])))-((a['rad']*10)*Math.cos(a['time'])))-a['time'])))); a['thresh']=((above(a['bass_att'], a['thresh'])*2)+((1-above(a['bass_att'], a['thresh']))*(((a['thresh']-1.3)*0.96)+1.3))); a['dx_r']=(((equal(a['thresh'], 2)*0.015)*Math.sin((5*a['time'])))+((1-equal(a['thresh'], 2))*a['dx_r'])); a['dy_r']=(((equal(a['thresh'], 2)*0.015)*Math.sin((6*a['time'])))+((1-equal(a['thresh'], 2))*a['dy_r'])); a['dx']=(a['dx_r']+(0.005*Math.sin((a['time']*1.463)))); a['dy']=(a['dy_r']+(0.005*Math.sin((a['time']*1.222))));","warp":" shader_body { \n  vec2 tmpvar_1;\n  tmpvar_1.x = roam_cos.x;\n  tmpvar_1.y = roam_sin.x;\n  vec3 tmpvar_2;\n  tmpvar_2.x = (0.918 + (0.05 * q2));\n  tmpvar_2.y = (0.912 + (0.05 * q3));\n  tmpvar_2.z = (0.905 + (0.05 * q1));\n  vec4 tmpvar_3;\n  tmpvar_3.w = 1.0;\n  tmpvar_3.xyz = (mix (texture (sampler_fw_main, uv).xyz, vec3((8.0 * texture (sampler_noise_hq, \n    (uv - (tmpvar_1 * 0.8))\n  ).x)), vec3(0.015, 0.015, 0.015)) * tmpvar_2);\n  ret = tmpvar_3.xyz;\n }","comp":" shader_body { \n  vec2 uvm_1;\n  vec3 ret_2;\n  uvm_1.x = (uv.x - (0.07 * texture (sampler_noise_hq, vec2((uv.x * 0.8))).x));\n  uvm_1.y = (uv.y - (0.07 * texture (sampler_noise_hq, vec2((uv.y * 0.8))).x));\n  vec4 tmpvar_3;\n  tmpvar_3 = texture (sampler_main, fract(uvm_1));\n  vec3 tmpvar_4;\n  tmpvar_4 = (((10.0 * tmpvar_3.xyz) - (\n    ((texture (sampler_blur1, uvm_1).xyz * scale1) + bias1)\n   * rad)) * ((0.8 * tmpvar_3.xyz) + cos(\n    (((rad * 2.0) - (roam_sin * 2.0)) + time)\n  ).xyz).x);\n  vec3 tmpvar_5;\n  tmpvar_5 = (1.0 - tmpvar_4);\n  vec2 tmpvar_6;\n  tmpvar_6.x = uv.x;\n  tmpvar_6.y = (uv.y * 0.75);\n  ret_2 = ((texture (sampler_main, tmpvar_6).xyz * tmpvar_5) + (0.55 * tmpvar_4));\n  vec3 tmpvar_7;\n  tmpvar_7 = mix (ret_2, tmpvar_5, vec3((1.5 * clamp (\n    dot (tmpvar_4, tmpvar_5)\n  , 0.0, 1.0))));\n  ret_2 = tmpvar_7;\n  vec4 tmpvar_8;\n  tmpvar_8.w = 1.0;\n  tmpvar_8.xyz = tmpvar_7;\n  ret = tmpvar_8.xyz;\n }"}