{"version":2,"baseVals":{"rating":5,"gammaadj":1.98,"decay":0.5,"echo_zoom":1,"echo_alpha":0.5,"echo_orient":3,"wave_mode":6,"additivewave":1,"wave_thick":1,"modwavealphabyvolume":1,"wave_brighten":0,"wrap":0,"darken":1,"wave_a":4.1,"wave_scale":1.733,"wave_smoothing":0,"wave_mystery":-0.42,"modwavealphastart":0.51,"modwavealphaend":1.7,"warpscale":1.331,"zoom":0.99951,"dx":0.005,"warp":0.01,"wave_r":0.81,"wave_g":0.67,"wave_b":0.54,"wave_x":0.66,"wave_y":1,"ob_size":0.005,"ob_a":1,"ib_size":0,"ib_r":0,"ib_g":0,"ib_b":0,"ib_a":1,"mv_x":64,"mv_y":1.248,"mv_l":5,"mv_b":0,"mv_a":0,"b1ed":0},"shapes":[{"baseVals":{"enabled":0},"init_eqs_str":"","frame_eqs_str":""},{"baseVals":{"enabled":0},"init_eqs_str":"","frame_eqs_str":""},{"baseVals":{"enabled":1,"sides":13,"thickoutline":1,"num_inst":359,"rad":0.31716,"tex_zoom":0.01291,"r":0.88,"g":0.75,"b":0.73,"a":0.01,"g2":0,"border_a":0.4},"init_eqs_str":"a['rx2'] = 0; a['is'] = 0; a['num'] = 0; a['sample'] = 0; ","frame_eqs_str":"a['r']=((a['r']*0.5)-a['rx2']); a['g']=(a['r']*0.8); a['b']=(a['g']*0.8); a['border_a']=(a['rx2']*0.0000001); a['is']=a['instance']; a['num']=a['num_inst']; a['sample']=div((a['is']+0.5),a['num']); a['x']=a['sample']; a['rx2']=((a['sample']*0.04)+(0.02*Math.sin(a['time'])));"},{"baseVals":{"enabled":0},"init_eqs_str":"","frame_eqs_str":""}],"waves":[{"baseVals":{"enabled":0},"init_eqs_str":"","frame_eqs_str":"","point_eqs_str":""},{"baseVals":{"enabled":0},"init_eqs_str":"","frame_eqs_str":"","point_eqs_str":""},{"baseVals":{"enabled":1,"samples":196,"sep":256,"spectrum":1,"usedots":1,"thick":1,"smoothing":0,"g":0.8,"b":0.7},"init_eqs_str":"a['timsec'] = 0; a['simp'] = 0; a['is'] = 0; a['bal'] = 0; a['pie'] = 0; a['instance'] = 0; a['x2'] = 0; a['y2'] = 0; a['num'] = 0; a['tims'] = 0; a['v1'] = 0; a['pi2'] = 0; a['v2'] = 0; a['samples'] = 0; a['s5'] = 0; a['num']=(a['sample']*a['samples']);","frame_eqs_str":"a['timsec']=(div(1,a['fps'])+a['timsec']); a['tims']=div(a['timsec'],Math.floor(a['timsec']));","point_eqs_str":"a['v1']=(a['value1']+Math.abs(a['value1'])); a['v2']=(a['value2']+Math.abs(a['value2'])); a['bal']=(a['v2']-a['v1']); a['reg17']=a['v1']; a['reg18']=a['v2']; a['reg19']=a['bal']; a['pie']=div(22,7); a['pi2']=(a['pie']*2); a['simp']=((a['sample']*2)-1); a['num']=a['samples']; a['instance']=(a['sample']*a['num']); a['is']=a['instance']; a['s5']=(a['sample']*0.5); a['r']=(0.5+(0.2*Math.sin((a['v2']-a['v1'])))); a['g']=((a['r']*0.65)+(0.15*Math.sin((a['time']*0.24)))); a['b']=((a['g']*0.76)+(0.1*Math.cos((a['time']*0.20)))); a['x2']=((a['value2']-a['value1'])+a['bal']); a['y2']=((a['s5']*2)-1); a['x2']=(a['x2']*0.5); a['y2']=(a['y2']*0.5); a['x']=(a['x2']+0.5); a['y']=(a['y2']+0.5);"},{"baseVals":{"enabled":1,"sep":256,"spectrum":1,"smoothing":0,"g":0.8,"b":0.7,"a":0.2},"init_eqs_str":"a['timsec'] = 0; a['simp'] = 0; a['is'] = 0; a['bal'] = 0; a['pie'] = 0; a['instance'] = 0; a['x2'] = 0; a['vol'] = 0; a['y2'] = 0; a['num'] = 0; a['tims'] = 0; a['v1'] = 0; a['pi2'] = 0; a['v2'] = 0; a['samples'] = 0; a['s5'] = 0; a['num']=(a['sample']*a['samples']);","frame_eqs_str":"a['timsec']=(div(1,a['fps'])+a['timsec']); a['tims']=div(a['timsec'],Math.floor(a['timsec']));","point_eqs_str":"a['v1']=(a['value1']+Math.abs(a['value1'])); a['v2']=(a['value2']+Math.abs(a['value2'])); a['bal']=(a['v2']-a['v1']); a['reg17']=a['v1']; a['reg18']=a['v2']; a['reg19']=a['bal']; a['pie']=div(22,7); a['pi2']=(a['pie']*2); a['simp']=((a['sample']*2)-1); a['num']=a['samples']; a['instance']=(a['sample']*a['num']); a['is']=a['instance']; a['s5']=(a['sample']*0.5); a['vol']=((div((a['sample']*((a['bass']+a['mid'])+a['treb'])),a['pi2'])+div((a['sample']*((a['bass_att']+a['mid_att'])+a['treb_att'])),a['pi2']))-(a['sample']*1.5)); a['a']=div(1,a['mid_att']); a['r']=(0.5+(0.2*Math.sin((a['v2']-a['v1'])))); a['g']=((a['r']*0.65)+(0.15*Math.sin((a['time']*0.24)))); a['b']=((a['g']*0.76)+(0.1*Math.cos((a['time']*0.20)))); a['x2']=a['vol']; a['y2']=((a['s5']*2)-1); a['x2']=(a['x2']*0.5); a['y2']=(a['y2']*0.21); a['x']=((a['x2']+0.5)+((a['bal']*2)*a['sample'])); a['y']=(a['y2']+0.5);"}],"init_eqs_str":"a['when'] = 0; a['mm'] = 0; a['mt'] = 0;","frame_eqs_str":"a['wave_a']=0; a['decay']=1; a['warp']=0; a['dx']=0; a['dy']=0; a['sx']=1; a['sy']=1; a['when']=0; a['mm']=(a['mm']+(((a['mid']*a['mid'])*a['mid'])*0.02)); a['mm']=(below(a['mm'], 628)*a['mm']); a['mt']=(a['mt']+(((a['bass']*a['bass'])*a['bass'])*0.02)); a['mt']=(below(a['mt'], 628)*a['mt']); a['rot']=(((Math.abs(equal(a['when'], 0))>0.00001)?(((Math.sin((a['mt']*0.1))*2)+2)):(0))-2); a['zoom']=((Math.abs(equal(a['when'], 0))>0.00001)?((1-((Math.sin(a['mm'])*0.2)+0.2))):(1)); a['monitor']=a['mt']; a['cx']=((Math.sin(a['time'])*0.035)+0.5); a['cy']=((Math.cos(a['time'])*0.035)+0.5);","pixel_eqs_str":"","warp":"uniform sampler2D sampler_rand00;\n shader_body { \n  vec3 ret_1;\n  ret_1 = (texture (sampler_main, uv).zxz * 0.8);\n  ret_1 = (ret_1 + ((texture (sampler_rand00, uv).xyz * 0.69) - (ret_1 * 0.4901)));\n  vec4 tmpvar_2;\n  tmpvar_2.w = 1.0;\n  tmpvar_2.xyz = ret_1;\n  ret = tmpvar_2.xyz;\n }","comp":"vec3 xlat_mutableeq;\nvec3 xlat_mutableteq;\n shader_body { \n  vec2 x_1;\n  x_1 = (uv - 0.5);\n  vec3 tmpvar_2;\n  tmpvar_2.x = max (1.0, bass_att);\n  tmpvar_2.y = max (1.0, mid_att);\n  tmpvar_2.z = max (1.0, treb_att);\n  vec3 tmpvar_3;\n  tmpvar_3.x = (time - bass);\n  tmpvar_3.y = (time - mid);\n  tmpvar_3.z = (time - treb);\n  xlat_mutableteq = (tmpvar_3 + (1.0/(tmpvar_2)));\n  xlat_mutableeq = (tmpvar_2 * (0.5 + (0.5 * \n    sin(xlat_mutableteq)\n  )));\n  vec3 tmpvar_4;\n  tmpvar_4.xy = (uv - vec2(0.5, 0.5));\n  tmpvar_4.z = (sqrt(dot (x_1, x_1)) - 0.5);\n  xlat_mutableeq = (xlat_mutableeq * (1.0 + (\n    (tmpvar_4 * (0.5 + (0.5 * abs(\n      cos(xlat_mutableteq)\n    ))))\n   * 0.5)));\n  vec2 tmpvar_5;\n  tmpvar_5.x = (1.0 - uv.x);\n  tmpvar_5.y = uv.y;\n  vec3 tmpvar_6;\n  tmpvar_6 = mix ((texture (sampler_main, uv).xyz / xlat_mutableeq), (texture (sampler_main, tmpvar_5).xyz / xlat_mutableeq), vec3(((0.5 * \n    max (max ((1.0/(xlat_mutableeq.x)), max ((1.0/(xlat_mutableeq.y)), (1.0/(xlat_mutableeq.z)))), max ((1.0 - (1.0/(xlat_mutableeq.x))), max ((1.0 - \n      (1.0/(xlat_mutableeq.y))\n    ), (1.0 - \n      (1.0/(xlat_mutableeq.z))\n    ))))\n  ) - 0.5)));\n  vec4 tmpvar_7;\n  tmpvar_7.w = 1.0;\n  tmpvar_7.xyz = (tmpvar_6 - vec3(ivec3(tmpvar_6)));\n  ret = tmpvar_7.xyz;\n }"}